ethiomultlib/__init__.py
ethiomultlib/ethiopian_arithmetic.py
ethiomultlib-0.1.0.dist-info/METADATA
ethiomultlib-0.1.0.dist-info/WHEEL
ethiomultlib-0.1.0.dist-info/top_level.txt
ethiomultlib-0.1.0.dist-info/RECORD
