Metadata-Version: 2.1
Name: ethiomultlib
Version: 0.1.0
Summary: A Python library for Ethiopian Multiplication.
Home-page: https://github.com/yourusername/ethiomultlib
Author: Daniel Gessese Amdework
Author-email: dnlmdwrk@gmail.com
License: MIT
Project-URL: Source, https://github.com/yourusername/ethiomultlib
Classifier: Development Status :: 3 - Alpha
Classifier: Intended Audience :: Education
Classifier: License :: OSI Approved :: MIT License
Classifier: Programming Language :: Python :: 3
Classifier: Programming Language :: Python :: 3.6
Classifier: Programming Language :: Python :: 3.7
Classifier: Programming Language :: Python :: 3.8
Classifier: Programming Language :: Python :: 3.9
Classifier: Programming Language :: Python :: 3.10
Classifier: Programming Language :: Python :: 3.11
Requires-Python: >=3.6
